README.md
setup.cfg
setup.py
mutexp/__init__.py
mutexp.egg-info/PKG-INFO
mutexp.egg-info/SOURCES.txt
mutexp.egg-info/dependency_links.txt
mutexp.egg-info/requires.txt
mutexp.egg-info/top_level.txt