Metadata-Version: 1.1
Name: mutexp
Version: 1.0.1
Summary: Predict mutation-specific expression from DNA features
Home-page: https://github.com/openvax/mutexp
Author: Alex Rubinsteyn
Author-email: alex@openvax.org
License: http://www.apache.org/licenses/LICENSE-2.0.html
Platform: UNKNOWN
Classifier: Development Status :: 3 - Alpha
Classifier: Environment :: Console
Classifier: Operating System :: OS Independent
Classifier: Intended Audience :: Science/Research
Classifier: License :: OSI Approved :: Apache Software License
Classifier: Programming Language :: Python
Classifier: Topic :: Scientific/Engineering :: Bio-Informatics
